src/__init__.py
text_preprocessor/__init__.py
text_preprocessor/preprocessor.py
text_preprocessor/utils.py
text_preprocessor_v1-0.1.0.dist-info/LICENSE
text_preprocessor_v1-0.1.0.dist-info/METADATA
text_preprocessor_v1-0.1.0.dist-info/WHEEL
text_preprocessor_v1-0.1.0.dist-info/RECORD
