Metadata-Version: 2.1
Name: text_preprocessor_v1
Version: 0.1.0
Summary: An advance text pre-processor
License: License
Author: deepakpant
Author-email: deepak.93p@gmail.com
Requires-Python: >=3.12,<4.0
Classifier: License :: Other/Proprietary License
Classifier: Programming Language :: Python :: 3
Classifier: Programming Language :: Python :: 3.12
Classifier: Programming Language :: Python :: 3.13
Requires-Dist: beautifulsoup4 (>=4.12.3,<5.0.0)
Requires-Dist: gensim (>=4.3.3,<5.0.0)
Requires-Dist: kaggle (>=1.6.17,<2.0.0)
Requires-Dist: kagglehub (>=0.3.4,<0.4.0)
Requires-Dist: nltk (>=3.9.1,<4.0.0)
Requires-Dist: pandas (>=2.2.3,<3.0.0)
